jupyter_require/__about__.py
jupyter_require/__init__.py
jupyter_require/core.py
jupyter_require/magic.py
jupyter_require/notebook.py
jupyter_require/static/core.js
jupyter_require/static/display.js
jupyter_require/static/extension.js
jupyter_require/static/loader.js
jupyter_require/static/logger.js
jupyter_require-0.6.1.data/data/etc/jupyter/nbconfig/notebook.d/jupyter-require.json
jupyter_require-0.6.1.data/data/share/jupyter/nbextensions/jupyter-require/core.js
jupyter_require-0.6.1.data/data/share/jupyter/nbextensions/jupyter-require/display.js
jupyter_require-0.6.1.data/data/share/jupyter/nbextensions/jupyter-require/extension.js
jupyter_require-0.6.1.data/data/share/jupyter/nbextensions/jupyter-require/loader.js
jupyter_require-0.6.1.data/data/share/jupyter/nbextensions/jupyter-require/logger.js
jupyter_require-0.6.1.dist-info/LICENSE
jupyter_require-0.6.1.dist-info/METADATA
jupyter_require-0.6.1.dist-info/WHEEL
jupyter_require-0.6.1.dist-info/top_level.txt
jupyter_require-0.6.1.dist-info/RECORD
