Metadata-Version: 2.1
Name: jupyter-require
Version: 0.6.1
Summary: Jupyter nbextension for JavaScript execution and managing linked libraries and CSS stylesheets in Jupyter notebooks.
Home-page: https://github.com/CermakM/jupyter-require
Author: Marek Cermak
Author-email: macermak@redhat.com
License: MIT
Platform: UNKNOWN
Classifier: Development Status :: 2 - Pre-Alpha
Classifier: Framework :: IPython
Classifier: Framework :: Jupyter
Classifier: License :: OSI Approved :: MIT License
Classifier: Natural Language :: English
Classifier: Operating System :: OS Independent
Classifier: Programming Language :: JavaScript
Classifier: Programming Language :: Python :: 3.5
Classifier: Programming Language :: Python :: 3.6
Classifier: Programming Language :: Python :: 3.7
Classifier: Topic :: Scientific/Engineering :: Visualization
Classifier: Topic :: Utilities
